pubkeeper/brew/local/__init__.py
pubkeeper/brew/local/brew.py
pubkeeper/brew/local/patron.py
pubkeeper/brew/local/server.py
pubkeeper.brew.local-2.0.0.dist-info/DESCRIPTION.rst
pubkeeper.brew.local-2.0.0.dist-info/METADATA
pubkeeper.brew.local-2.0.0.dist-info/RECORD
pubkeeper.brew.local-2.0.0.dist-info/WHEEL
pubkeeper.brew.local-2.0.0.dist-info/metadata.json
pubkeeper.brew.local-2.0.0.dist-info/top_level.txt
