Metadata-Version: 2.0
Name: pubkeeper.brew.local
Version: 2.0.0
Summary: Brew, Consume, Local
Home-page: http://github.com/pubkeeper/python-brew-local
Author: n.io
Author-email: info@n.io
License: UNKNOWN
Keywords: pubkeeper,python-brew-local
Platform: UNKNOWN
Classifier: License :: Other/Proprietary License
Classifier: Programming Language :: Python :: 3
Classifier: Programming Language :: Python :: 3.5
Requires-Dist: pubkeeper.client (~=1.0)
